{
    "objects": [
        {
            "type": "Star",
            "R": 2.0,
            "color": "red",
            "m": 1.98892e+30,
            "x": 0.0,
            "y": 0.0,
            "Vx": 0.0,
            "Vy": 0.0
        },
        {
            "type": "Planet",
            "R": 2.0,
            "color": "orange",
            "m": 3.302e+23,
            "x": 57909000000.0,
            "y": 0.0,
            "Vx": 0.0,
            "Vy": 47870.0
        },
        {
            "type": "Planet",
            "R": 5.0,
            "color": "blue",
            "m": 4.869e+24,
            "x": 108210000000.0,
            "y": 0.0,
            "Vx": 0.0,
            "Vy": 35020.0
        },
        {
            "type": "Planet",
            "R": 5.0,
            "color": "green",
            "m": 5.974e+24,
            "x": 149600000000.0,
            "y": 0.0,
            "Vx": 0.0,
            "Vy": 29760.0
        },
        {
            "type": "Planet",
            "R": 3.0,
            "color": "red",
            "m": 6.419e+23,
            "x": 227940000000.0,
            "y": 0.0,
            "Vx": 0.0,
            "Vy": 24130.0
        },
        {
            "type": "Planet",
            "R": 20.0,
            "color": "yellow",
            "m": 1.899e+27,
            "x": 778410000000.0,
            "y": 0.0,
            "Vx": 0.0,
            "Vy": 13070.0
        },
        {
            "type": "Planet",
            "R": 15.0,
            "color": "white",
            "m": 5.685e+26,
            "x": 1429400000000.0,
            "y": 0.0,
            "Vx": 0.0,
            "Vy": 9670.0
        }
    ]
}